{
  "next": 2,
  "data": [
    {
      "ID": 1,
      "Data de Chegada": "22-03-2021",
      "Peso de Chegada em Kg": "30",
      "Peso @": "1",
      "Lote": "1",
      "Tamanho": "U"
    },
    {
      "ID": 2,
      "Data de Chegada": "22-03-2021",
      "Peso de Chegada em Kg": "30",
      "Peso @": "1",
      "Lote": "1",
      "Tamanho": "U"
    },
    {
      "ID": 3,
      "Data de Chegada": "22-03-2021",
      "Peso de Chegada em Kg": "30",
      "Peso @": "1",
      "Lote": "1",
      "Tamanho": "U"
    },
    {
      "ID": 4,
      "Data de Chegada": "22-03-2021",
      "Peso de Chegada em Kg": "30",
      "Peso @": "1",
      "Lote": "1",
      "Tamanho": "U"
    },
    {
      "ID": 5,
      "Data de Chegada": "22-03-2021",
      "Peso de Chegada em Kg": "30",
      "Peso @": "1",
      "Lote": "1",
      "Tamanho": "U"
    },
    {
      "ID": 6,
      "Data de Chegada": "22-03-2021",
      "Peso de Chegada em Kg": "30",
      "Peso @": "1",
      "Lote": "1",
      "Tamanho": "U"
    },
    {
      "ID": 7,
      "Data de Chegada": "22-03-2021",
      "Peso de Chegada em Kg": "30",
      "Peso @": "1",
      "Lote": "1",
      "Tamanho": "U"
    },
    {
      "ID": 8,
      "Data de Chegada": "22-03-2021",
      "Peso de Chegada em Kg": "30",
      "Peso @": "1",
      "Lote": "1",
      "Tamanho": "U"
    },
    {
      "ID": 9,
      "Data de Chegada": "22-03-2021",
      "Peso de Chegada em Kg": "30",
      "Peso @": "1",
      "Lote": "1",
      "Tamanho": "U"
    },
    {
      "ID": 10,
      "Data de Chegada": "22-03-2021",
      "Peso de Chegada em Kg": "30",
      "Peso @": "1",
      "Lote": "1",
      "Tamanho": "U"
    },
    {
      "ID": 11,
      "Data de Chegada": "22-03-2021",
      "Peso de Chegada em Kg": "30",
      "Peso @": "1",
      "Lote": "1",
      "Tamanho": "U"
    },
    {
      "ID": 12,
      "Data de Chegada": "22-03-2021",
      "Peso de Chegada em Kg": "30",
      "Peso @": "1",
      "Lote": "1",
      "Tamanho": "U"
    },
    {
      "ID": 13,
      "Data de Chegada": "22-03-2021",
      "Peso de Chegada em Kg": "30",
      "Peso @": "1",
      "Lote": "1",
      "Tamanho": "U"
    },
    {
      "ID": 14,
      "Data de Chegada": "22-03-2021",
      "Peso de Chegada em Kg": "30",
      "Peso @": "1",
      "Lote": "1",
      "Tamanho": "U"
    },
    {
      "ID": 15,
      "Data de Chegada": "22-03-2021",
      "Peso de Chegada em Kg": "30",
      "Peso @": "1",
      "Lote": "1",
      "Tamanho": "U"
    }
  ]
}